counterfusion/__init__.py
counterfusion/algorithm.py
counterfusion/interface.py
counterfusion/utils.py
counterfusion-0.1.1.dist-info/LICENSE
counterfusion-0.1.1.dist-info/METADATA
counterfusion-0.1.1.dist-info/WHEEL
counterfusion-0.1.1.dist-info/top_level.txt
counterfusion-0.1.1.dist-info/RECORD
