Metadata-Version: 2.1
Name: counterfusion
Version: 0.1.1
Summary: A light-weight package to solve large systems of interactions
Home-page: https://github.com/LarsonLaugh/Counterfusion
Author: Lixian Wang
Author-email: lixianphys@gmail.com
License: UNKNOWN
Platform: UNKNOWN
Classifier: Programming Language :: Python :: 3
Classifier: Operating System :: OS Independent
Requires-Python: >=3.8
License-File: LICENSE
Requires-Dist: numpy (>=1.20.1)
Requires-Dist: matplotlib (>=3.4.3)
